Metadata-Version: 1.0
Name: sej
Version: 0.1
Summary: Chinese Segmentation Tool
Home-page: UNKNOWN
Author: begosu
Author-email: cocaer.cl@gmail.com
License: MIT Licence
Keywords: pip,Chinese,segmentation,HMM
Platform: any
